odoo/addons/hr_employee_ssn/README.rst
odoo/addons/hr_employee_ssn/__init__.py
odoo/addons/hr_employee_ssn/__manifest__.py
odoo/addons/hr_employee_ssn/i18n/fr.po
odoo/addons/hr_employee_ssn/i18n/hr_employee_ssn.pot
odoo/addons/hr_employee_ssn/i18n/it.po
odoo/addons/hr_employee_ssn/readme/CONTRIBUTORS.rst
odoo/addons/hr_employee_ssn/readme/DESCRIPTION.rst
odoo/addons/hr_employee_ssn/static/description/icon.png
odoo/addons/hr_employee_ssn/static/description/index.html
odoo/addons/hr_employee_ssn/views/hr_employee_views.xml
odoo12_addon_hr_employee_ssn-12.0.1.0.0.99.dev11.dist-info/METADATA
odoo12_addon_hr_employee_ssn-12.0.1.0.0.99.dev11.dist-info/WHEEL
odoo12_addon_hr_employee_ssn-12.0.1.0.0.99.dev11.dist-info/top_level.txt
odoo12_addon_hr_employee_ssn-12.0.1.0.0.99.dev11.dist-info/RECORD
